MANIFEST.in
README.md
VERSION.txt
setup.cfg
setup.py
src/gary_test_package/__init__.py
src/gary_test_package/gary_test.py
src/gary_test_package.egg-info/PKG-INFO
src/gary_test_package.egg-info/SOURCES.txt
src/gary_test_package.egg-info/dependency_links.txt
src/gary_test_package.egg-info/entry_points.txt
src/gary_test_package.egg-info/top_level.txt