Metadata-Version: 2.4
Name: gary-test-package
Version: 1.0.29
Summary: This is a test package and is only a hello world app.
Home-page: 
Author: Gary Schaetz
Author-email: gary@schaetzkc.com
License: MIT
Dynamic: author
Dynamic: author-email
Dynamic: description
Dynamic: description-content-type
Dynamic: keywords
Dynamic: license
Dynamic: summary
